.gitignore
CHANGES.txt
LICENSE.txt
MANIFEST.in
README.rst
setup.py
cloudfrontsigner/__init__.py
cloudfrontsigner/cfsign.py
cloudfrontsigner/compat.py
cloudfrontsigner.egg-info/PKG-INFO
cloudfrontsigner.egg-info/SOURCES.txt
cloudfrontsigner.egg-info/dependency_links.txt
cloudfrontsigner.egg-info/entry_points.txt
cloudfrontsigner.egg-info/not-zip-safe
cloudfrontsigner.egg-info/requires.txt
cloudfrontsigner.egg-info/top_level.txt
cloudfrontsigner/tests/__init__.py
cloudfrontsigner/tests/test_cfsign.py
cloudfrontsigner/tests/test_cloudfrontsigner.py
cloudfrontsigner/tests/test_functional.py
cloudfrontsigner/tests/testkey1.pem