Metadata-Version: 1.1
Name: cloudfrontsigner
Version: 0.1
Summary: Generate AWS CloudFront's Signed URLs
Home-page: https://github.com/gjo/cloudfrontsigner
Author: OCHIAI, Gouji
Author-email: gjo.ext@gmail.com
License: BSD
Platform: UNKNOWN
Classifier: Development Status :: 4 - Beta
Classifier: Intended Audience :: Developers
Classifier: Intended Audience :: System Administrators
Classifier: License :: OSI Approved :: BSD License
Classifier: Programming Language :: Python
Classifier: Programming Language :: Python :: 2.7
Classifier: Programming Language :: Python :: 3.3
Classifier: Programming Language :: Python :: 3.4
Classifier: Programming Language :: Python :: 3.5
